{
    "site": "grenoble",
    "nodes": {
        "100": {
            "x": 1.0,
            "y": 25.23,
            "z": -0.04,
            "uid": "b080"
        },
        "102": {
            "x": 1.0,
            "y": 24.63,
            "z": -0.04,
            "uid": "a881"
        },
        "117": {
            "x": 0.4,
            "y": 19.83,
            "z": -0.04,
            "uid": "2262"
        },
        "108": {
            "x": 1.0,
            "y": 22.83,
            "z": -0.04,
            "uid": "8477"
        },
        "115": {
            "x": 0.4,
            "y": 20.43,
            "z": -0.04,
            "uid": "8471"
        },
        "107": {
            "x": 0.4,
            "y": 22.83,
            "z": -0.04,
            "uid": "a072"
        },
        "110": {
            "x": 1.0,
            "y": 22.23,
            "z": -0.04,
            "uid": "a071"
        },
        "113": {
            "x": 0.4,
            "y": 21.03,
            "z": -0.04,
            "uid": "a671"
        },
        "103": {
            "x": 0.4,
            "y": 24.03,
            "z": -0.04,
            "uid": "9881"
        },
        "105": {
            "x": 0.4,
            "y": 23.43,
            "z": -0.04,
            "uid": "b576"
        },
        "101": {
            "x": 0.4,
            "y": 24.63,
            "z": -0.04,
            "uid": "9181"
        },
        "118": {
            "x": 1.0,
            "y": 19.83,
            "z": -0.04,
            "uid": "9376"
        },
        "111": {
            "x": 0.4,
            "y": 21.63,
            "z": -0.04,
            "uid": "9172"
        },
        "114": {
            "x": 1.0,
            "y": 21.03,
            "z": -0.04,
            "uid": "a879"
        },
        "112": {
            "x": 1.0,
            "y": 21.63,
            "z": -0.04,
            "uid": "a578"
        },
        "106": {
            "x": 1.0,
            "y": 23.43,
            "z": -0.04,
            "uid": "9382"
        },
        "109": {
            "x": 0.4,
            "y": 22.23,
            "z": -0.04,
            "uid": "1062"
        },
        "116": {
            "x": 1.0,
            "y": 20.43,
            "z": -0.04,
            "uid": "8969"
        },
        "119": {
            "x": 0.4,
            "y": 19.23,
            "z": -0.04,
            "uid": "a468"
        },
        "104": {
            "x": 1.0,
            "y": 24.03,
            "z": -0.04,
            "uid": "a775"
        }
    }
}